[
    [
        {
            "title": "Senior Software Developer - Full Stack Developer",
            "company_name": "Royal Bank of Canada",
            "location": "Raleigh, NC",
            "link": "https://www.google.com/search?q=full+stack+developer&gl=US&hl=en&uule=w+CAIQICIiMjg0MzksTm9ydGggQ2Fyb2xpbmEsVW5pdGVkIFN0YXRlcw%3D%3D&udm=8#vhid=vt%3D20/docid%3D0Kp-3ZlYfOxOZ8W5AAAAAA%3D%3D&vssid=jobs-detail-viewer",
            "via": "RBC Careers"
        },
        {
            "title": "Senior Software Developer - Full Stack Developer",
            "company_name": "Royal Bank of Canada",
            "location": "Anywhere",
            "link": "https://www.google.com/search?q=full+stack+developer&gl=US&hl=en&uule=w+CAIQICIiMjg0MzksTm9ydGggQ2Fyb2xpbmEsVW5pdGVkIFN0YXRlcw%3D%3D&udm=8#vhid=vt%3D20/docid%3DJha6Mav4P9ROZm3PAAAAAA%3D%3D&vssid=jobs-detail-viewer",
            "via": "Indeed"
        },
        {
            "title": "Full Stack Developer",
            "company_name": "TMPC",
            "location": "Fayetteville, NC",
            "link": "https://www.google.com/search?q=full+stack+developer&gl=US&hl=en&uule=w+CAIQICIiMjg0MzksTm9ydGggQ2Fyb2xpbmEsVW5pdGVkIFN0YXRlcw%3D%3D&udm=8#vhid=vt%3D20/docid%3Dso6v1krfG817lLbiAAAAAA%3D%3D&vssid=jobs-detail-viewer",
            "via": "Indeed"
        },
        {
            "title": "Full Stack Developer",
            "company_name": "Cognizant",
            "location": "Durham, NC",
            "link": "https://www.google.com/search?q=full+stack+developer&gl=US&hl=en&uule=w+CAIQICIiMjg0MzksTm9ydGggQ2Fyb2xpbmEsVW5pdGVkIFN0YXRlcw%3D%3D&udm=8#vhid=vt%3D20/docid%3D5AXyd1ruBvB3BihoAAAAAA%3D%3D&vssid=jobs-detail-viewer",
            "via": "Cognizant Careers"
        },
        {
            "title": "Senior Full Stack Developer",
            "company_name": "Genesys",
            "location": "Carolina Beach, NC",
            "link": "https://www.google.com/search?q=full+stack+developer&gl=US&hl=en&uule=w+CAIQICIiMjg0MzksTm9ydGggQ2Fyb2xpbmEsVW5pdGVkIFN0YXRlcw%3D%3D&udm=8#vhid=vt%3D20/docid%3DObMZLIgZknZun-gFAAAAAA%3D%3D&vssid=jobs-detail-viewer",
            "via": "Ladders"
        },
        {
            "title": "Software Developer (Full-stack)",
            "company_name": "SAS",
            "location": "Cary, NC",
            "link": "https://www.google.com/search?q=full+stack+developer&gl=US&hl=en&uule=w+CAIQICIiMjg0MzksTm9ydGggQ2Fyb2xpbmEsVW5pdGVkIFN0YXRlcw%3D%3D&udm=8#vhid=vt%3D20/docid%3DJ3Sf0LLZTAhJJ6bcAAAAAA%3D%3D&vssid=jobs-detail-viewer",
            "via": "Indeed"
        },
        {
            "title": "Full Stack Developer Jobs",
            "company_name": "TEKsystems c/o Allegis Group",
            "location": "North Carolina",
            "link": "https://www.google.com/search?q=full+stack+developer&gl=US&hl=en&uule=w+CAIQICIiMjg0MzksTm9ydGggQ2Fyb2xpbmEsVW5pdGVkIFN0YXRlcw%3D%3D&udm=8#vhid=vt%3D20/docid%3DKVHHZfo9RmkDlJHPAAAAAA%3D%3D&vssid=jobs-detail-viewer",
            "via": "Security Clearance Jobs"
        },
        {
            "title": "Jr. Full Stack Developer-Backend Focused",
            "company_name": "Secmation",
            "location": "Cary, NC",
            "link": "https://www.google.com/search?q=full+stack+developer&gl=US&hl=en&uule=w+CAIQICIiMjg0MzksTm9ydGggQ2Fyb2xpbmEsVW5pdGVkIFN0YXRlcw%3D%3D&udm=8#vhid=vt%3D20/docid%3DqoakDhZg4cY3-Fn4AAAAAA%3D%3D&vssid=jobs-detail-viewer",
            "via": "ZipRecruiter"
        },
        {
            "title": "AI-Native Software Engineer (Full Stack)",
            "company_name": "Flow RMS",
            "location": "Raleigh, NC",
            "link": "https://www.google.com/search?q=full+stack+developer&gl=US&hl=en&uule=w+CAIQICIiMjg0MzksTm9ydGggQ2Fyb2xpbmEsVW5pdGVkIFN0YXRlcw%3D%3D&udm=8#vhid=vt%3D20/docid%3DrIuwmkmN9t_FAK1JAAAAAA%3D%3D&vssid=jobs-detail-viewer",
            "via": "SimplyHired"
        },
        {
            "title": "Full Stack Developer",
            "company_name": "Chariot",
            "location": "Raleigh, NC",
            "link": "https://www.google.com/search?q=full+stack+developer&gl=US&hl=en&uule=w+CAIQICIiMjg0MzksTm9ydGggQ2Fyb2xpbmEsVW5pdGVkIFN0YXRlcw%3D%3D&udm=8#vhid=vt%3D20/docid%3DEBbuTEvuscuvbJlTAAAAAA%3D%3D&vssid=jobs-detail-viewer",
            "via": "Chariot Creative"
        }
    ]
]